pyblish/__init__.py
pyblish/__main__.py
pyblish/api.py
pyblish/cli.py
pyblish/compat.py
pyblish/error.py
pyblish/lib.py
pyblish/logic.py
pyblish/main.py
pyblish/plugin.py
pyblish/util.py
pyblish/version.py
pyblish/icons/logo-32x32.svg
pyblish/icons/logo-64x64.svg
pyblish/plugins/collect_current_date.py
pyblish/plugins/collect_current_user.py
pyblish/plugins/collect_current_working_directory.py
pyblish/vendor/__init__.py
pyblish/vendor/iscompatible.py
pyblish/vendor/mock.py
pyblish/vendor/six.py
pyblish/vendor/click/__init__.py
pyblish/vendor/click/_bashcomplete.py
pyblish/vendor/click/_compat.py
pyblish/vendor/click/_termui_impl.py
pyblish/vendor/click/_textwrap.py
pyblish/vendor/click/core.py
pyblish/vendor/click/decorators.py
pyblish/vendor/click/exceptions.py
pyblish/vendor/click/formatting.py
pyblish/vendor/click/parser.py
pyblish/vendor/click/termui.py
pyblish/vendor/click/testing.py
pyblish/vendor/click/types.py
pyblish/vendor/click/utils.py
tests/__init__.py
tests/lib.py
tests/plugins.py
tests/test_cli.py
tests/test_context.py
tests/test_events.py
tests/test_logic.py
tests/test_misc.py
tests/test_plugin.py
tests/test_simple.py
tests/test_util.py
tests/pre11/__init__.py
tests/pre11/lib.py
tests/pre11/test_cli.py
tests/pre11/test_logic.py
tests/pre11/test_plugins.py
tests/pre13/__init__.py
tests/pre13/test_di.py
tests/pre13/test_logic.py
tests/pre13/test_plugin.py
pyblish_base-1.8.12.dist-info/LICENSE.txt
pyblish_base-1.8.12.dist-info/METADATA
pyblish_base-1.8.12.dist-info/WHEEL
pyblish_base-1.8.12.dist-info/entry_points.txt
pyblish_base-1.8.12.dist-info/top_level.txt
pyblish_base-1.8.12.dist-info/RECORD
